mr/__init__.py
mr/config/__init__.py
mr/mime.py
mr/states/__init__.py
mr/states/implementations/__init__.py
mr/states/implementations/memory.py
mr/states/implementations/redis.py
mr/states/implementations/temp.py
mr/states/interface.py
my_mimic-0.5.2.dist-info/LICENSE
my_mimic-0.5.2.dist-info/METADATA
my_mimic-0.5.2.dist-info/WHEEL
my_mimic-0.5.2.dist-info/RECORD
