Metadata-Version: 2.3
Name: my-mimic
Version: 0.5.2
Summary: Cache/Memoization package
License: Apache-2.0
Author: Marco Sievers de Almeida Ximit Gaia
Author-email: im.ximit@gmail.com
Requires-Python: >=3.10,<4.0
Classifier: License :: OSI Approved :: Apache Software License
Classifier: Programming Language :: Python :: 3
Classifier: Programming Language :: Python :: 3.10
Classifier: Programming Language :: Python :: 3.11
Classifier: Programming Language :: Python :: 3.12
Classifier: Programming Language :: Python :: 3.13
Provides-Extra: redis-edition
Provides-Extra: temp-edition
Requires-Dist: aiofile (>=3.8.8,<4.0.0) ; extra == "temp-edition"
Requires-Dist: meeseeks-singleton (>=0.4.2,<0.5.0)
Requires-Dist: redis (>=5.0.8,<6.0.0) ; extra == "redis-edition"
Project-URL: documentation, https://github.com/CenturyBoys/my-mimic
Project-URL: homepage, https://github.com/CenturyBoys/my-mimic
Project-URL: repository, https://github.com/CenturyBoys/my-mimic
